{
  "solicitacoes": [
    {
      "id": 1,
      "nomeEmpresa": "Money Money Invest",
      "faturamentoAnual": 180000,
      "valorSolicitado": 20000,
      "cnpj": 131232131,
      "rua": "Rua Neto da Silva",
      "numero": 658,
      "cep": "12430242-09",
      "cidade": "São Paulo",
      "estado": "São Paulo",
      "bairro": "Pinheiros",
      "nomeResponsavel": "Daniel",
      "telefone": "11 949594000",
      "email": "algo@moneymoney.com.br",
      "cpf": "123123131"
    },
    {
      "id": 2,
      "nomeEmpresa": "Montreal Viagens",
      "faturamentoAnual": 180000,
      "valorSolicitado": 20000,
      "cnpj": 131232131,
      "rua": "Rua Neto da Silva",
      "numero": 658,
      "cep": "12430242-09",
      "cidade": "São Paulo",
      "estado": "São Paulo",
      "bairro": "Pinheiros",
      "nomeResponsavel": "Daniel",
      "telefone": "11 949594000",
      "email": "algo@moneymoney.com.br",
      "cpf": "123123131"
    },
    {
      "id": 3,
      "nomeEmpresa": "Tesouraria Junior",
      "faturamentoAnual": 180000,
      "valorSolicitado": 20000,
      "cnpj": 131232131,
      "rua": "Rua Neto da Silva",
      "numero": 658,
      "cep": "12430242-09",
      "cidade": "São Paulo",
      "estado": "São Paulo",
      "bairro": "Pinheiros",
      "nomeResponsavel": "Daniel",
      "telefone": "11 949594000",
      "email": "algo@moneymoney.com.br",
      "cpf": "123123131"
    }
  ]
}